check_glue_catalog/__init__.py
check_glue_catalog/check_glue_catalog.py
check_glue_catalog/utils.py
check_glue_catalog-0.1.9.dist-info/LICENSE
check_glue_catalog-0.1.9.dist-info/METADATA
check_glue_catalog-0.1.9.dist-info/WHEEL
check_glue_catalog-0.1.9.dist-info/top_level.txt
check_glue_catalog-0.1.9.dist-info/RECORD
