Metadata-Version: 2.1
Name: check-glue-catalog
Version: 0.1.9
Summary: Check for details in Glue Catalog and tell if its outdated
Home-page: https://github.com/msantino/check-glue-catalog
Author: Marcelo Santino
Author-email: eu@marcelosantino.com.br
License: UNKNOWN
Platform: UNKNOWN
Classifier: Programming Language :: Python :: 3
Classifier: License :: OSI Approved :: MIT License
Classifier: Operating System :: OS Independent
Requires-Dist: boto3
